AUTHORS.rst
CONTRIBUTING.rst
HISTORY.rst
LICENSE
MANIFEST.in
README.rst
setup.py
fabric_pgbackup/__init__.py
fabric_pgbackup/config-sample.py
fabric_pgbackup/db.py
fabric_pgbackup/fabric-pgbackup.py
fabric_pgbackup/utils.py
fabric_pgbackup.egg-info/PKG-INFO
fabric_pgbackup.egg-info/SOURCES.txt
fabric_pgbackup.egg-info/dependency_links.txt
fabric_pgbackup.egg-info/not-zip-safe
fabric_pgbackup.egg-info/requires.txt
fabric_pgbackup.egg-info/top_level.txt