Metadata-Version: 1.1
Name: fabric-pgbackup
Version: 0.1.0
Summary: PostgreSQL backup/restore utilities for Fabric
Home-page: https://github.com/zalew/fabric-pgbackup
Author: Jakub Zalewski
Author-email: zalew7@gmail.com
License: MIT
Keywords: fabric-pgbackup
Platform: UNKNOWN
Classifier: Development Status :: 2 - Pre-Alpha
Classifier: Intended Audience :: Developers
Classifier: License :: OSI Approved :: MIT License
Classifier: Natural Language :: English
Classifier: Programming Language :: Python :: 2
Classifier: Programming Language :: Python :: 2.6
Classifier: Programming Language :: Python :: 2.7
